em05/__init__.py
em05/em05.py
em05-0.1.0.dist-info/licenses/LICENSE
em05-0.1.0.dist-info/METADATA
em05-0.1.0.dist-info/WHEEL
em05-0.1.0.dist-info/top_level.txt
em05-0.1.0.dist-info/RECORD
