Metadata-Version: 2.4
Name: em05
Version: 0.1.0
Summary: Python library for Quectel EM05 cellular module SMS operations
Home-page: https://github.com/rikki/em05-sms
Author: Rikki
Author-email: Rikki <i@rikki.moe>
License: MIT
Project-URL: Homepage, https://github.com/rikki/em05-sms
Project-URL: Bug Reports, https://github.com/rikki/em05-sms/issues
Project-URL: Source, https://github.com/rikki/em05-sms
Keywords: sms,cellular,quectel,em05,at-commands
Classifier: Development Status :: 3 - Alpha
Classifier: Intended Audience :: Developers
Classifier: License :: OSI Approved :: MIT License
Classifier: Operating System :: OS Independent
Classifier: Programming Language :: Python :: 3
Classifier: Programming Language :: Python :: 3.7
Classifier: Programming Language :: Python :: 3.8
Classifier: Programming Language :: Python :: 3.9
Classifier: Programming Language :: Python :: 3.10
Classifier: Programming Language :: Python :: 3.11
Classifier: Topic :: Communications :: Telephony
Classifier: Topic :: System :: Hardware
Classifier: Topic :: Software Development :: Libraries :: Python Modules
Requires-Python: >=3.7
License-File: LICENSE
Requires-Dist: pyserial>=3.4
Dynamic: author
Dynamic: home-page
Dynamic: license-file
Dynamic: requires-python
